robophisher/__init__.py
robophisher/arguments.py
robophisher/helper.py
robophisher/pyrobophisher.py
robophisher/common/__init__.py
robophisher/common/accesspoint.py
robophisher/common/constants.py
robophisher/common/extensions.py
robophisher/common/firewall.py
robophisher/common/interfaces.py
robophisher/common/macmatcher.py
robophisher/common/opmode.py
robophisher/common/phishinghttp.py
robophisher/common/recon.py
robophisher/common/uimethods.py
robophisher/data/wifiphisher-mac-prefixes
robophisher/data/cert/server.pem
robophisher/data/locs/.gitkeep
robophisher/data/phishing-pages/firmware-upgrade/bootstrap.min.css
robophisher/data/phishing-pages/firmware-upgrade/bootstrap.min.js
robophisher/data/phishing-pages/firmware-upgrade/config.ini
robophisher/data/phishing-pages/firmware-upgrade/index.html
robophisher/data/phishing-pages/firmware-upgrade/jquery.min.js
robophisher/data/phishing-pages/firmware-upgrade/loading.html
robophisher/data/phishing-pages/firmware-upgrade/upgrading.html
robophisher/data/phishing-pages/firmware-upgrade/static/bootstrap.min.css
robophisher/data/phishing-pages/firmware-upgrade/static/bootstrap.min.js
robophisher/data/phishing-pages/firmware-upgrade/static/jquery.min.js
robophisher/data/phishing-pages/oauth-login/config.ini
robophisher/data/phishing-pages/oauth-login/index.html
robophisher/data/phishing-pages/oauth-login/license.txt
robophisher/data/phishing-pages/oauth-login/oauth.html
robophisher/data/phishing-pages/oauth-login/css/font-awesome.min.css
robophisher/data/phishing-pages/oauth-login/css/reset.css
robophisher/data/phishing-pages/oauth-login/css/roboto.css
robophisher/data/phishing-pages/oauth-login/css/style.css
robophisher/data/phishing-pages/oauth-login/js/index.js
robophisher/data/phishing-pages/oauth-login/js/jquery.min.js
robophisher/data/phishing-pages/oauth-login/static/css/font-awesome.min.css
robophisher/data/phishing-pages/oauth-login/static/css/reset.css
robophisher-1.3.0.dist-info/DESCRIPTION.rst
robophisher-1.3.0.dist-info/METADATA
robophisher-1.3.0.dist-info/RECORD
robophisher-1.3.0.dist-info/WHEEL
robophisher-1.3.0.dist-info/entry_points.txt
robophisher-1.3.0.dist-info/metadata.json
robophisher-1.3.0.dist-info/top_level.txt
