Metadata-Version: 2.0
Name: robophisher
Version: 1.3.0
Summary: Automated phishing attacks against Wi-Fi networks
Home-page: https://github.com/blackHatMonkey/RoboPhisher
Author: blackHatMonkey
Author-email: brian.smith@riseup.net
License: GPL
Keywords: robophisher,evil,twin,phishing
Platform: UNKNOWN
Classifier: Development Status :: 5 - Production/Stable
Classifier: License :: OSI Approved :: GNU Lesser General Public License v3 (LGPLv3)
Classifier: Natural Language :: English
Classifier: Operating System :: Unix
Classifier: Programming Language :: Python :: 2
Classifier: Programming Language :: Python :: 2.7
Classifier: Programming Language :: Python :: 2 :: Only
Classifier: Topic :: Security
Classifier: Topic :: System :: Networking
Classifier: Intended Audience :: End Users/Desktop
Classifier: Intended Audience :: System Administrators
Classifier: Intended Audience :: Information Technology
Requires-Dist: PyRIC
Requires-Dist: tornado
Requires-Dist: pbkdf2
Requires-Dist: roguehostapd
